pysco/__init__.py
pysco/cosmotable.py
pysco/cubic.py
pysco/fourier.py
pysco/initial_conditions.py
pysco/integration.py
pysco/iostream.py
pysco/laplacian.py
pysco/laplacian_reformulated.py
pysco/main.py
pysco/mesh.py
pysco/mond.py
pysco/morton.py
pysco/multigrid.py
pysco/numpy_atomic.py
pysco/quartic.py
pysco/solver.py
pysco/utils.py
pysco_nbody-1.0.9.dist-info/METADATA
pysco_nbody-1.0.9.dist-info/WHEEL
pysco_nbody-1.0.9.dist-info/entry_points.txt
pysco_nbody-1.0.9.dist-info/licenses/LICENSE
pysco_nbody-1.0.9.dist-info/RECORD
