Metadata-Version: 2.1
Name: pysco-nbody
Version: 1.0.9
Summary: A Python library to run N-body simulations with modified gravity
Author-Email: =?utf-8?q?Michel-Andr=C3=A8s_Breton?= <michel-andres.breton@obspm.fr>
Classifier: Programming Language :: Python :: 3
Classifier: License :: OSI Approved :: MIT License
Classifier: Operating System :: OS Independent
Project-URL: Homepage, https://github.com/mianbreton/pysco
Requires-Python: <3.14,>=3.11
Requires-Dist: numpy
Requires-Dist: matplotlib
Requires-Dist: astropy
Requires-Dist: numba
Requires-Dist: pandas
Requires-Dist: scipy
Requires-Dist: pyarrow
Requires-Dist: h5py
Requires-Dist: rich
Requires-Dist: icc-rt
Requires-Dist: pyfftw
